molellipsize/__init__.py
molellipsize/ellipsefitter.py
molellipsize/molecule.py
molellipsize/utilities.py
tests/__init__.py
tests/ellipsefitter/__init__.py
tests/ellipsefitter/conftest.py
tests/ellipsefitter/test_ellipsefitter.py
tests/molecule/__init__.py
tests/molecule/conftest.py
tests/molecule/test_molecule.py
mol_ellipsize-1.0.2.dist-info/LICENSE
mol_ellipsize-1.0.2.dist-info/METADATA
mol_ellipsize-1.0.2.dist-info/WHEEL
mol_ellipsize-1.0.2.dist-info/top_level.txt
mol_ellipsize-1.0.2.dist-info/RECORD
