Metadata-Version: 2.1
Name: mol-ellipsize
Version: 1.0.2
Summary: Ellipsoid fitting over conformer ensembles for calculating size.
Home-page: https://github.com/andrewtarzia/mol-ellipsize
Author: Andrew Tarzia
Author-email: andrew.tarzia@gmail.com
License: UNKNOWN
Platform: UNKNOWN
Classifier: Programming Language :: Python :: 3
Classifier: License :: OSI Approved :: GNU General Public License v3 (GPLv3)
Classifier: Operating System :: OS Independent
Requires-Python: >=3.6
Requires-Dist: matplotlib
Requires-Dist: numpy
